{
  "name": "Yancy footer",
  "type": "footer",
  "sections": {
    "yancy-footer": {
      "type": "yancy-footer",
      "blocks": {
        "shop": {
          "type": "link_list",
          "settings": { "heading": "Shop", "menu": "" }
        },
        "company": {
          "type": "link_list",
          "settings": { "heading": "Company", "menu": "" }
        }
      },
      "block_order": ["shop", "company"],
      "settings": {
        "logo_text": "YANCY",
        "tagline": "Colombian handmade textile studio.",
        "show_social": true
      }
    }
  },
  "order": ["yancy-footer"]
}
